{
  "slug": "rashford-emoji-combos",
  "title": "Rashford Emoji Combos рЯПіу†БІу†БҐу†Б•у†БЃу†БІу†БњвЪљрЯРР Copy & Paste",
  "meta_description": "Rashford emoji combos рЯПіу†БІу†БҐу†Б•у†БЃу†БІу†БњвЪљ вАФ fan emoji sets for bios, captions, and comments. Click any emoji or combo to copy it instantly.",
  "breadcrumb": "Rashford Emoji Combos",
  "hero_h1": "Rashford Emoji Combos",
  "hero_tagline": "Fan emoji sets for Rashford вАФ flag, football, and signature combos. Click any emoji or combo to copy it.",
  "intro": "Marcus Rashford fans pair the England flag рЯПіу†БІу†БҐу†Б•у†БЃу†БІу†Бњ with the ball вЪљ and lightning pace вЪ°. These combos suit fan bios, captions, and comments. Copy a single emoji below, or grab a full combo set with one click.",
  "canonical": "https://ultratextgen.com/library/rashford-emoji-combos/",
  "date_published": "2026-06-14",
  "date_modified": "2026-06-14",
  "copy_pattern": "collection",
  "sections": [
    {
      "id": "rashford-emojis",
      "label": "Rashford",
      "h2": "Rashford Emojis",
      "intro": "The signature emojis for the player.",
      "symbols": [
        {
          "char": "рЯПіу†БІу†БҐу†Б•у†БЃу†БІу†Бњ",
          "label": "England Flag"
        },
        {
          "char": "вЪљ",
          "label": "Soccer Ball"
        },
        {
          "char": "рЯРР",
          "label": "GOAT"
        },
        {
          "char": "вЪ°",
          "label": "Lightning (Pace)"
        },
        {
          "char": "рЯФЯ",
          "label": "Number 10"
        },
        {
          "char": "рЯПЖ",
          "label": "Trophy"
        },
        {
          "char": "рЯФі",
          "label": "Red (Man United)"
        },
        {
          "char": "рЯ¶Б",
          "label": "Lion (Three Lions)"
        }
      ]
    },
    {
      "id": "england-emojis",
      "label": "England",
      "h2": "England & Man United Emojis",
      "intro": "The United forward and England star.",
      "symbols": [
        {
          "char": "рЯПіу†БІу†БҐу†Б•у†БЃу†БІу†Бњ",
          "label": "England Flag"
        },
        {
          "char": "рЯФі",
          "label": "Red Circle"
        },
        {
          "char": "вЪ°",
          "label": "Lightning"
        },
        {
          "char": "рЯ¶Б",
          "label": "Lion"
        },
        {
          "char": "рЯТ®",
          "label": "Dashing Away"
        },
        {
          "char": "рЯПЖ",
          "label": "Trophy"
        }
      ]
    }
  ],
  "collection_section": {
    "id": "combo-sets",
    "label": "Combo Sets",
    "h2": "Rashford Combo Sets",
    "intro": "Copy a full combo in one click and paste it into a bio, caption, or username."
  },
  "collection_container_id": "rashfordCombosContainer",
  "collections": [
    {
      "name": "Marcus",
      "flags": [
        "рЯПіу†БІу†БҐу†Б•у†БЃу†БІу†Бњ",
        "вЪљ",
        "рЯФі"
      ],
      "defaultFormat": "inline"
    },
    {
      "name": "United Red",
      "flags": [
        "рЯФі",
        "вЪљ",
        "рЯФ•"
      ],
      "defaultFormat": "inline"
    },
    {
      "name": "England Star",
      "flags": [
        "рЯПіу†БІу†БҐу†Б•у†БЃу†БІу†Бњ",
        "вЪљ",
        "рЯ¶Б"
      ],
      "defaultFormat": "inline"
    },
    {
      "name": "Speed",
      "flags": [
        "вЪ°",
        "вЪљ",
        "рЯТ®"
      ],
      "defaultFormat": "inline"
    }
  ],
  "related": [
    {
      "href": "/library/world-cup-emoji-combos/",
      "title": "World Cup Emoji Combos",
      "desc": "World Cup emoji sets and combos for fan bios and captions."
    },
    {
      "href": "/library/football-symbols/",
      "title": "Football Symbols",
      "desc": "Soccer and football symbols, trophies, and match combos."
    },
    {
      "href": "/library/emoji-flags/",
      "title": "Flag Emojis",
      "desc": "Country and regional flag emojis ready to copy and paste."
    },
    {
      "href": "/library/emoji-combos/",
      "title": "Emoji Combos",
      "desc": "Aesthetic emoji combinations for every mood and theme."
    }
  ]
}
